Metadata-Version: 2.1
Name: jsonrpclib
Version: 0.2.1
Summary: Implementation of the JSON-RPC v2.0 specification (backwards-compatible) as a client library.
Home-page: https://github.com/joshmarshall/jsonrpclib
Author: Josh Marshall
Author-email: catchjosh@gmail.com
License: UNKNOWN
Platform: UNKNOWN
Requires-Python: >=3.5
